{"is_source_file": false, "format": "", "description": "", "external_files": [], "external_methods": [], "published": [], "classes": [], "methods": [], "calls": [], "search-terms": ["music-center", "student registration", "87320-87329"], "state": 2, "file_id": 12, "knowledge_revision": 22, "git_revision": "56e6ffdc9f6c2244d97a70ee96b5a165bbe6526a", "hash": "16b50c68509ffc51626d6aec4f65e2fb", "format-version": 4, "code-base-name": "music_center_student_registration_frontend", "filename": "README.md", "revision_history": [{"22": "56e6ffdc9f6c2244d97a70ee96b5a165bbe6526a"}]}